colorize_pinyin/__init__.py
colorize_pinyin/__main__.py
colorize_pinyin-2.1.1.dist-info/DESCRIPTION.rst
colorize_pinyin-2.1.1.dist-info/entry_points.txt
colorize_pinyin-2.1.1.dist-info/METADATA
colorize_pinyin-2.1.1.dist-info/metadata.json
colorize_pinyin-2.1.1.dist-info/pbr.json
colorize_pinyin-2.1.1.dist-info/RECORD
colorize_pinyin-2.1.1.dist-info/top_level.txt
colorize_pinyin-2.1.1.dist-info/WHEEL
