Metadata-Version: 2.0
Name: colorize-pinyin
Version: 2.1.1
Summary: search for chinese pinyin and wrap it with HTML.
Home-page: https://github.com/ratijas/colorize_pinyin
Author: Ratijas
Author-email: ratijas.t@me.com
License: WTFPL
Keywords: find search chinese pinyin tones colorize
Platform: UNKNOWN
Classifier: Development Status :: 5 - Production/Stable
Classifier: Intended Audience :: Developers
Classifier: Environment :: Plugins
Classifier: Topic :: Education
Classifier: Topic :: Text Processing
Classifier: Topic :: Text Processing :: Linguistic
Classifier: License :: Public Domain
Classifier: Programming Language :: Python :: 2
Classifier: Programming Language :: Python :: 2.7
Classifier: Programming Language :: Python :: 3
Classifier: Programming Language :: Python :: 3.4
